{
    "active": true,
    "altitude": 130.21,
    "cluster": "Sussex",
    "country": "United Kingdom",
    "latitude": 50.8654752,
    "longitude": -0.0857853,
    "name": "University of Sussex",
    "number": 15001,
    "scintillators": [
        {
            "alpha": null,
            "beta": null,
            "height": null,
            "radius": null
        },
        {
            "alpha": null,
            "beta": null,
            "height": null,
            "radius": null
        }
    ],
    "subcluster": "Sussex"
}